mongoengine_softdelete/__init__.py
mongoengine_softdelete/document.py
mongoengine_softdelete/queryset.py
mongoengine_softdelete/signals.py
mongoengine_softdelete-0.0.10.dist-info/WHEEL
mongoengine_softdelete-0.0.10.dist-info/METADATA
mongoengine_softdelete-0.0.10.dist-info/RECORD
