Metadata-Version: 2.1
Name: mongoengine-softdelete
Version: 0.0.10
Summary: Soft delete for MongoEngine
Home-page: https://github.com/dolead/mongoengine-softdelete
License: MIT
Keywords: mongoengine,soft,delete
Author: Benjamin Hirschfield
Author-email: benjamin.hirschfield@dolead.com
Maintainer: Benjamin Hirschfield
Maintainer-email: benjamin.hirschfield@dolead.com
Requires-Python: >=3.7,<4.0
Classifier: License :: OSI Approved :: MIT License
Classifier: Programming Language :: Python :: 3
Classifier: Programming Language :: Python :: 3.10
Classifier: Programming Language :: Python :: 3.7
Classifier: Programming Language :: Python :: 3.8
Classifier: Programming Language :: Python :: 3.9
Requires-Dist: mongoengine (>=0.16.3)
Requires-Dist: pymongo (>=3.6.1)
Project-URL: Repository, https://github.com/dolead/mongoengine-softdelete
